cuser/__init__.py
cuser/apps.py
cuser/compat.py
cuser/fields.py
cuser/middleware.py
cuser/models.py
cuser/views.py
django_cuser-2017.3.16.dist-info/DESCRIPTION.rst
django_cuser-2017.3.16.dist-info/METADATA
django_cuser-2017.3.16.dist-info/RECORD
django_cuser-2017.3.16.dist-info/WHEEL
django_cuser-2017.3.16.dist-info/metadata.json
django_cuser-2017.3.16.dist-info/top_level.txt
testproject/__init__.py
testproject/settings.py
testproject/urls.py
testproject/wsgi.py
testproject/testapp/__init__.py
testproject/testapp/admin.py
testproject/testapp/apps.py
testproject/testapp/models.py
testproject/testapp/tests.py
testproject/testapp/views.py
testproject/testapp/migrations/0001_initial.py
testproject/testapp/migrations/__init__.py
